lanms_pytorch-1.0.3.data/purelib/lanms/__init__.py
lanms_pytorch-1.0.3.data/purelib/lanms/liblanms.dylib
lanms_pytorch-1.0.3.dist-info/LICENSE
lanms_pytorch-1.0.3.dist-info/METADATA
lanms_pytorch-1.0.3.dist-info/WHEEL
lanms_pytorch-1.0.3.dist-info/top_level.txt
lanms_pytorch-1.0.3.dist-info/RECORD
