Metadata-Version: 2.1
Name: lanms-pytorch
Version: 1.0.3
Summary: Locality-Aware Non-Maximum Suppression, as a custom C++ operator in TorchScript.
Home-page: https://github.com/xhdhr10000/lanms
Author: argmen (boostczc@gmail.com) is code author, Dominik Walder (dominik.walder@parquery.com) and Marko Ristin (marko@parquery.com) only packaged the code, xhdhr10000 (xhdhr2007@126.com) ported to TorchScript framework
Author-email: xhdhr2007@126.com
License: GNU General Public License v3.0
Keywords: locality aware non-maximum suppression
Platform: UNKNOWN
Classifier: Development Status :: 5 - Production/Stable
Classifier: Intended Audience :: Developers
Classifier: Topic :: Scientific/Engineering :: Artificial Intelligence
Classifier: License :: OSI Approved :: GNU General Public License v3 (GPLv3)
Classifier: Programming Language :: Python :: 3.5
Requires-Dist: torch (>=1.6.0)
